matrix7/__init__.py
matrix7/matrix7.py
matrix7-1.2.0.dist-info/LICENSE
matrix7-1.2.0.dist-info/METADATA
matrix7-1.2.0.dist-info/WHEEL
matrix7-1.2.0.dist-info/top_level.txt
matrix7-1.2.0.dist-info/RECORD
