Metadata-Version: 2.1
Name: matrix7
Version: 1.2.0
Summary: Matrix and Vector Manipulation library
Home-page: https://github.com/LogX7/Matrix7
Author: Mohamed Benkedadra
Author-email: hammicristo@gmail.com
License: UNKNOWN
Platform: UNKNOWN
Classifier: Programming Language :: Python :: 3
Classifier: License :: OSI Approved :: GNU General Public License v3 or later (GPLv3+)
Classifier: Operating System :: OS Independent
Classifier: Intended Audience :: Education
Classifier: Intended Audience :: Information Technology
Classifier: Topic :: Education
Classifier: Natural Language :: English
